strathisla/__init__.py
strathisla/eft.py
strathisla/nuisance_parameters.py
strathisla/variable_covariance.py
strathisla-1.0.0.dist-info/licenses/LICENSE
strathisla-1.0.0.dist-info/METADATA
strathisla-1.0.0.dist-info/WHEEL
strathisla-1.0.0.dist-info/entry_points.txt
strathisla-1.0.0.dist-info/top_level.txt
strathisla-1.0.0.dist-info/RECORD
