Metadata-Version: 2.4
Name: strathisla
Version: 1.0.0
Summary: Likelihood plugins for the Spey package
Author-email: Joe Egan <joseph.caimin.egan@cern.ch>
License-Expression: MIT
Project-URL: Homepage, https://github.com/joes-git/strathisla
Project-URL: Bug Reports, https://github.com/joes-git/strathisla/issues
Project-URL: Source, https://github.com/joes-git/strathisla
Keywords: high energy physics,statistics,particle physics,spey,likelihood,EFT,fitting,re-interpretation,BSM
Classifier: Development Status :: 3 - Alpha
Classifier: Intended Audience :: Science/Research
Classifier: Programming Language :: Python :: 3
Classifier: Programming Language :: Python :: 3.9
Classifier: Programming Language :: Python :: 3.10
Classifier: Programming Language :: Python :: 3.11
Classifier: Programming Language :: Python :: 3.12
Requires-Python: >=3.9
License-File: LICENSE
Requires-Dist: spey>=0.1.11
Requires-Dist: numpy>=1.21.0
Requires-Dist: scipy>=1.7.0
Provides-Extra: dev
Requires-Dist: pytest>=6.0; extra == "dev"
Requires-Dist: pytest-cov>=2.0; extra == "dev"
Requires-Dist: black>=22.0; extra == "dev"
Requires-Dist: isort>=5.0; extra == "dev"
Requires-Dist: flake8>=4.0; extra == "dev"
Dynamic: license-file
